power_analysis/__init__.py
power_analysis/Examples.py
power_analysis/PanelBoostrapObs.py
power_analysis/SimpleBootstrap.py
power_analysis-0.1.5.dist-info/LICENSE
power_analysis-0.1.5.dist-info/METADATA
power_analysis-0.1.5.dist-info/WHEEL
power_analysis-0.1.5.dist-info/RECORD
