Metadata-Version: 2.1
Name: power-analysis
Version: 0.1.5
Summary: This package allows you to perform power analysis computations
License: MIT
Author: Rodrigo Franco
Author-email: franc703@umn.edu
Requires-Python: >=3.7,<3.10
Classifier: License :: OSI Approved :: MIT License
Classifier: Programming Language :: Python :: 3
Classifier: Programming Language :: Python :: 3.7
Classifier: Programming Language :: Python :: 3.8
Classifier: Programming Language :: Python :: 3.9
Requires-Dist: numpy (>=1.16.5,<1.23.0)
Requires-Dist: optional-py (>=1.3.2,<2.0.0)
Requires-Dist: scipy (>=1.7.0,<=1.7.1)
